picflow/__init__.py
picflow/cli.py
picflow/info.py
picflow/core/__init__.py
picflow/core/config.py
picflow/core/processor.py
picflow/processors/__init__.py
picflow/processors/webp.py
picflow/uploaders/__init__.py
picflow/uploaders/qiniu.py
picflow/utils/__init__.py
picflow/utils/logger.py
picflow/utils/qr.py
picflow-0.1.4.dist-info/LICENSE
picflow-0.1.4.dist-info/METADATA
picflow-0.1.4.dist-info/WHEEL
picflow-0.1.4.dist-info/entry_points.txt
picflow-0.1.4.dist-info/top_level.txt
picflow-0.1.4.dist-info/RECORD
