Metadata-Version: 2.1
Name: picflow
Version: 0.1.4
Summary: CLI tool for image processing and uploading to cloud storage.
Home-page: https://github.com/luhuadong/picflow
Author: luhuadong
Author-email: luhuadong@163.com
License: MIT
Project-URL: Bug Tracker, https://github.com/luhuadong/picflow/issues
Classifier: Programming Language :: Python :: 3
Classifier: License :: OSI Approved :: MIT License
Classifier: Operating System :: OS Independent
Requires-Python: >=3.8
License-File: LICENSE
Requires-Dist: click>=8.1.0
Requires-Dist: pyyaml>=6.0
Requires-Dist: requests>=2.28.0
Requires-Dist: qiniu>=7.4.0
Requires-Dist: python-dotenv>=0.21.0
Requires-Dist: qrcode>=7.4.2
Requires-Dist: pillow>=9.0.0
Requires-Dist: exifread>=3.0.0
